Metadata-Version: 1.0
Name: gbg123-distributions
Version: 1.0
Summary: General, binomial and gaussian distributions
Home-page: UNKNOWN
Author: Pierre Liebenberg
Author-email: pierrelieb@gmail.com
License: UNKNOWN
Platform: UNKNOWN
